orf_news.py
ORF_News-2.0.0.dist-info/METADATA
ORF_News-2.0.0.dist-info/WHEEL
ORF_News-2.0.0.dist-info/license.txt
ORF_News-2.0.0.dist-info/top_level.txt
ORF_News-2.0.0.dist-info/RECORD
