Metadata-Version: 2.1
Name: ORF-News
Version: 2.0.0
Summary: Simple orf news scraper
Home-page: https://github.com/mcbabo/ORF_News_v2
Author: Moritz | mcbabo#6969
License: UNKNOWN
Platform: UNKNOWN
Classifier: Programming Language :: Python :: 3
Classifier: Programming Language :: Python :: 3.9
Classifier: Programming Language :: Python :: 3.10
Classifier: License :: OSI Approved :: MIT License
Classifier: Operating System :: OS Independent
License-File: license.txt
Requires-Dist: aiohttp (>=3.8)
Requires-Dist: bs4 (>=0.0.1)
Requires-Dist: beautifulsoup4 (>=4.10.0)
